{
  "id": "D0-30_osito",
  "titulo": "Osito",
  "descripcion": "Colorear un osito de peluche con mono",
  "tipo": "colorear",
  "materia": "dibujo",
  "nivel": "D0-30",
  "tema": "animales",
  "misiones": [
    {
      "id": "dib-osito-color-01",
      "tipo": "colorear",
      "titulo": "Osito",
      "emoji": "🧸",
      "instruccion": "Colorea el osito de peluche! Su mono puede ser de tu color favorito.",
      "imagen_contorno_url": "/dibujo/colorear/D0-30_osito.svg",
      "colores_sugeridos": ["#795548", "#e67e22", "#ff8fab", "#f1c40f"],
      "dificultad": "facil"
    }
  ]
}
